memprod/MemPrOD.py
memprod/__init__.py
memprod-0.0.9.dist-info/licenses/LICENSE
memprod-0.0.9.dist-info/METADATA
memprod-0.0.9.dist-info/WHEEL
memprod-0.0.9.dist-info/entry_points.txt
memprod-0.0.9.dist-info/top_level.txt
memprod-0.0.9.dist-info/RECORD
