Metadata-Version: 2.4
Name: memprod
Version: 0.0.9
Summary: A program for the prediction of local membrane deformations around a protein
Author-email: Matyas Parrag <matyas.parrag@gmail.com>
License-Expression: GPL-3.0
Project-URL: Homepage, https://github.com/ShufflerBardOnTheEdge/MemPrOD
Project-URL: Issues, https://github.com/ShufflerBardOnTheEdge/MemPrOD/issues
Classifier: Programming Language :: Python :: 3
Requires-Python: >=3.11
License-File: LICENSE
Requires-Dist: argparse>=1.4.0
Requires-Dist: mempro>=0.0.9
Requires-Dist: scipy>=1.11.3
Dynamic: license-file
